pyANN/__init__.py
pyANN/__version__.py
pyANN/core.py
pyANN/test.py
xskj_pyAnn-0.2.0.dist-info/LICENSE
xskj_pyAnn-0.2.0.dist-info/METADATA
xskj_pyAnn-0.2.0.dist-info/WHEEL
xskj_pyAnn-0.2.0.dist-info/top_level.txt
xskj_pyAnn-0.2.0.dist-info/RECORD
